objectutils/__init__.py
objectutils/class_wrapper.py
objectutils/main.py
objectutils/traverse.py
objectutils-0.3.0.dist-info/LICENSE
objectutils-0.3.0.dist-info/METADATA
objectutils-0.3.0.dist-info/WHEEL
objectutils-0.3.0.dist-info/top_level.txt
objectutils-0.3.0.dist-info/RECORD
