Metadata-Version: 2.1
Name: objectutils
Version: 0.3.0
Summary: Utils that extend default dict|list operations
Home-page: https://github.com/Chmele/difflib/tree/main
Author: Chmele
License: MIT
Keywords: dict,json,jq,jmespath
Classifier: Development Status :: 3 - Alpha
Classifier: Intended Audience :: Developers
Classifier: Topic :: Software Development :: Build Tools
Classifier: Programming Language :: Python :: 3
Classifier: Programming Language :: Python :: 3.10
Classifier: Programming Language :: Python :: 3.11
License-File: LICENSE
